setup.cfg
setup.py
stat_disp_sbp.egg-info/PKG-INFO
stat_disp_sbp.egg-info/SOURCES.txt
stat_disp_sbp.egg-info/dependency_links.txt
stat_disp_sbp.egg-info/not-zip-safe
stat_disp_sbp.egg-info/top_level.txt
stat_dist_sbp/Binomialdistribution.py
stat_dist_sbp/Gaussiandistribution.py
stat_dist_sbp/Generaldistribution.py
stat_dist_sbp/__init__.py